{
  "schemaVersion": 1,
  "id": "hcscr",
  "version": "${version}",
  "name": "HaramClientsideCrystalRemover",
  "description": "Remove your end crystals before the server even knows you hit 'em!",
  "authors": [
    "Offenderify",
    "VidTu"
  ],
  "contact": {
    "homepage": "https://github.com/FemboyPvE/HCsCR",
    "sources": "https://github.com/FemboyPvE/HCsCR",
    "issues": "https://github.com/FemboyPvE/HCsCR/issues",
    "email": "imvidtu@proton.me",
    "discord": "https://dsc.gg/femboypve"
  },
  "license": "Apache-2.0",
  "icon": "assets/hcscr/icon.png",
  "environment": "client",
  "entrypoints": {
    "client": [
      "ru.femboypve.hcscr.HCsCRFabric"
    ],
    "modmenu": [
      "ru.femboypve.hcscr.HCsCRModMenu"
    ]
  },
  "custom": {
    "modmenu": {
      "links": {
        "modmenu.discord": "https://dsc.gg/femboypve"
      }
    }
  },
  "mixins": [
    "hcscr.mixins.json"
  ],
  "depends": {
    "fabric-api": "*"
  },
  "recommends": {
    "modmenu": "*"
  }
}
